{
  "_class": "symbolInstance",
  "booleanOperation": -1,
  "do_objectID": "696EEACC-0F59-4501-BA4C-756A0947DC39",
  "exportOptions": {
    "_class": "exportOptions",
    "exportFormats": [
    ],
    "includedLayerIds": [
    ],
    "layerOptions": 0,
    "shouldTrim": false
  },
  "frame": {
    "_class": "rect",
    "constrainProportions": false,
    "do_objectID": "2B386833-90A4-4282-9F9B-77358B2AB1D6",
    "height": 50,
    "width": 50.12531328320802,
    "x": 16,
    "y": 5
  },
  "horizontalSpacing": 0,
  "isFixedToViewport": false,
  "isFlippedHorizontal": false,
  "isFlippedVertical": false,
  "isLocked": false,
  "isVisible": true,
  "layerListExpandedType": 0,
  "name": "img",
  "nameIsFixed": false,
  "overrideValues": [
  ],
  "resizingConstraint": 41,
  "resizingType": 0,
  "rotation": 0,
  "scale": 1,
  "shouldBreakMaskChain": false,
  "style": {
    "_class": "style",
    "do_objectID": "8D6361BB-10FB-4319-A99F-1CC6E128A636",
    "endMarkerType": 0,
    "miterLimit": 10,
    "startMarkerType": 0,
    "windingRule": 1
  },
  "symbolID": "C51040CC-57C7-4932-A403-DDCCE4541276",
  "verticalSpacing": 0
}