{
  "_class": "symbolInstance",
  "booleanOperation": -1,
  "do_objectID": "2CF2707C-EC20-4CC0-BD61-3F2C38A7AD84",
  "exportOptions": {
    "_class": "exportOptions",
    "exportFormats": [
    ],
    "includedLayerIds": [
    ],
    "layerOptions": 0,
    "shouldTrim": false
  },
  "frame": {
    "_class": "rect",
    "constrainProportions": false,
    "height": 35,
    "width": 65,
    "x": 245,
    "y": 0
  },
  "horizontalSpacing": 0,
  "isFixedToViewport": false,
  "isFlippedHorizontal": false,
  "isFlippedVertical": false,
  "isLocked": false,
  "isVisible": true,
  "layerListExpandedType": 0,
  "name": "filter",
  "nameIsFixed": true,
  "overrideValues": [
    {
      "_class": "overrideValue",
      "overrideName": "0DC2E19C-57A4-4C8C-8AEC-ADDB27CCF16D_stringValue",
      "value": "Filter"
    }
  ],
  "resizingConstraint": 44,
  "resizingType": 0,
  "rotation": 0,
  "scale": 1,
  "shouldBreakMaskChain": false,
  "style": {
    "_class": "style",
    "endMarkerType": 0,
    "miterLimit": 10,
    "startMarkerType": 0,
    "windingRule": 1
  },
  "symbolID": "5FE68B1F-D807-4866-8AB5-4C1951DEE23E",
  "verticalSpacing": 0
}