{
  "_class": "group",
  "booleanOperation": -1,
  "do_objectID": "3F62B30A-001A-47C0-9DB1-1C6888CBB4A3",
  "exportOptions": {
    "_class": "exportOptions",
    "exportFormats": [
    ],
    "includedLayerIds": [
    ],
    "layerOptions": 0,
    "shouldTrim": false
  },
  "frame": {
    "_class": "rect",
    "constrainProportions": false,
    "height": 46,
    "width": 47,
    "x": 17,
    "y": 5
  },
  "hasClickThrough": false,
  "isFixedToViewport": false,
  "isFlippedHorizontal": false,
  "isFlippedVertical": false,
  "isLocked": false,
  "isVisible": true,
  "layerListExpandedType": 0,
  "layers": [
    {
      "class": "shapeGroup",
      "id": "5F1483CA-749E-4459-A753-DAA56710625C"
    },
    {
      "class": "shapeGroup",
      "id": "1C6ABC23-C867-492D-A648-64D0A1E5474C"
    },
    {
      "class": "symbolInstance",
      "id": "88809BAE-3CEC-4E33-B93B-5110CE3326A9"
    }
  ],
  "name": "img",
  "nameIsFixed": false,
  "resizingConstraint": 63,
  "resizingType": 0,
  "rotation": 0,
  "shouldBreakMaskChain": false,
  "style": {
    "_class": "style",
    "endMarkerType": 0,
    "miterLimit": 10,
    "startMarkerType": 0,
    "windingRule": 1
  }
}