{
  "_class": "group",
  "booleanOperation": 0,
  "do_objectID": "7E3473C6-E1B8-4B2F-8385-2736885EDD33",
  "exportOptions": {
    "_class": "exportOptions",
    "exportFormats": [
    ],
    "includedLayerIds": [
    ],
    "layerOptions": 0,
    "shouldTrim": false
  },
  "frame": {
    "_class": "rect",
    "constrainProportions": false,
    "do_objectID": "1899E645-FAAA-4D67-B6F7-3B1BD7CEBC5A",
    "height": 32,
    "width": 99,
    "x": 0,
    "y": 0
  },
  "hasClickThrough": false,
  "isFixedToViewport": false,
  "isFlippedHorizontal": false,
  "isFlippedVertical": false,
  "isLocked": false,
  "isVisible": true,
  "layerListExpandedType": 0,
  "layers": [
    {
      "class": "group",
      "id": "DC49FB77-6C7D-4F70-9189-5E83260D85D3"
    },
    {
      "class": "text",
      "id": "0B789D91-F53C-4DCA-B84B-9E59AEA61868"
    }
  ],
  "name": "buttons/h32px/centered-label",
  "nameIsFixed": true,
  "resizingConstraint": 63,
  "resizingType": 0,
  "rotation": 0,
  "shouldBreakMaskChain": false,
  "style": {
    "_class": "style",
    "do_objectID": "413C71E0-5006-4A65-9A97-72CFE64DC9E4",
    "endMarkerType": 0,
    "miterLimit": 10,
    "startMarkerType": 0,
    "windingRule": 1
  }
}