{
  "_class": "symbolInstance",
  "booleanOperation": -1,
  "do_objectID": "C77DA683-D80B-4A99-AF37-B85FCF286D0E",
  "exportOptions": {
    "_class": "exportOptions",
    "exportFormats": [
    ],
    "includedLayerIds": [
    ],
    "layerOptions": 0,
    "shouldTrim": false
  },
  "frame": {
    "_class": "rect",
    "constrainProportions": false,
    "do_objectID": "0840325C-C99D-4A81-8064-77D7C21E4095",
    "height": 60,
    "width": 400,
    "x": 0,
    "y": 360
  },
  "horizontalSpacing": 0,
  "isFixedToViewport": false,
  "isFlippedHorizontal": false,
  "isFlippedVertical": false,
  "isLocked": false,
  "isVisible": true,
  "layerListExpandedType": 0,
  "name": "a- / action Item / enable",
  "nameIsFixed": false,
  "overrideValues": [
  ],
  "resizingConstraint": 63,
  "resizingType": 0,
  "rotation": 0,
  "scale": 1,
  "shouldBreakMaskChain": false,
  "style": {
    "_class": "style",
    "do_objectID": "15F1966B-0BA6-4525-8BBD-CB65A72C4F30",
    "endMarkerType": 0,
    "miterLimit": 10,
    "startMarkerType": 0,
    "windingRule": 1
  },
  "symbolID": "0B943E31-AB0C-4D19-AB04-25F9632A61B3",
  "verticalSpacing": 0
}