{
  "_class": "shapeGroup",
  "booleanOperation": -1,
  "clippingMaskMode": 0,
  "do_objectID": "8DFEDF62-25D5-4E8F-AC78-00DE198D816F",
  "exportOptions": {
    "_class": "exportOptions",
    "exportFormats": [
    ],
    "includedLayerIds": [
    ],
    "layerOptions": 0,
    "shouldTrim": false
  },
  "frame": {
    "_class": "rect",
    "constrainProportions": true,
    "do_objectID": "8034AE0C-A759-4FB9-AD2F-2D4FAA72C030",
    "height": 19.16666666666659,
    "width": 22,
    "x": 1,
    "y": 2
  },
  "hasClickThrough": false,
  "hasClippingMask": true,
  "isFixedToViewport": false,
  "isFlippedHorizontal": false,
  "isFlippedVertical": false,
  "isLocked": false,
  "isVisible": true,
  "layerListExpandedType": 1,
  "layers": [
    {
      "class": "shapePath",
      "id": "CDBA6063-29B3-4EC1-A2E8-B7379D43A24C"
    },
    {
      "class": "shapePath",
      "id": "091DC274-B58F-4502-9781-EC2D8E1EB5A6"
    }
  ],
  "name": "Mask",
  "nameIsFixed": false,
  "resizingConstraint": 63,
  "resizingType": 0,
  "rotation": 0,
  "shouldBreakMaskChain": false,
  "style": {
    "_class": "style",
    "do_objectID": "BB519934-BD61-452E-818E-459E7346208C",
    "endMarkerType": 0,
    "fills": [
      {
        "_class": "fill",
        "color": {
          "_class": "color",
          "alpha": 1,
          "blue": 0.9961473345756531,
          "green": 0.9987195134162903,
          "red": 1
        },
        "fillType": 0,
        "isEnabled": true,
        "noiseIndex": 0,
        "noiseIntensity": 0,
        "patternFillType": 1,
        "patternTileScale": 1
      }
    ],
    "miterLimit": 10,
    "startMarkerType": 0,
    "windingRule": 1
  },
  "windingRule": 1
}