{
  "_class": "symbolInstance",
  "booleanOperation": -1,
  "do_objectID": "244C3891-45AB-4580-B20B-D437754F3784",
  "exportOptions": {
    "_class": "exportOptions",
    "exportFormats": [
    ],
    "includedLayerIds": [
    ],
    "layerOptions": 0,
    "shouldTrim": false
  },
  "frame": {
    "_class": "rect",
    "constrainProportions": false,
    "height": 31,
    "width": 69,
    "x": 102,
    "y": 0
  },
  "horizontalSpacing": 0,
  "isFixedToViewport": false,
  "isFlippedHorizontal": false,
  "isFlippedVertical": false,
  "isLocked": false,
  "isVisible": true,
  "layerListExpandedType": 0,
  "name": "1",
  "nameIsFixed": true,
  "overrideValues": [
    {
      "_class": "overrideValue",
      "do_objectID": "638BF3A7-0855-4CB8-95AD-5973F45779A6",
      "overrideName": "C2302B50-81C3-4782-AC29-E43F7C806A03_stringValue",
      "value": "Activity"
    }
  ],
  "resizingConstraint": 63,
  "resizingType": 0,
  "rotation": 0,
  "scale": 1,
  "shouldBreakMaskChain": false,
  "style": {
    "_class": "style",
    "endMarkerType": 0,
    "miterLimit": 10,
    "startMarkerType": 0,
    "windingRule": 1
  },
  "symbolID": "698711A7-EAE8-4D92-B50E-D719CBBC9234",
  "verticalSpacing": 0
}