{
  "_class": "group",
  "booleanOperation": -1,
  "do_objectID": "76C11AA1-3324-4BE2-83F7-B29724BE7082",
  "exportOptions": {
    "_class": "exportOptions",
    "exportFormats": [
    ],
    "includedLayerIds": [
    ],
    "layerOptions": 0,
    "shouldTrim": false
  },
  "frame": {
    "_class": "rect",
    "constrainProportions": false,
    "height": 24,
    "width": 24,
    "x": 40,
    "y": 20
  },
  "hasClickThrough": false,
  "isFixedToViewport": false,
  "isFlippedHorizontal": false,
  "isFlippedVertical": false,
  "isLocked": false,
  "isVisible": true,
  "layerListExpandedType": 0,
  "layers": [
    {
      "class": "group",
      "id": "D0A2B4DB-0F8F-4890-9621-6F02CDDB607B"
    },
    {
      "class": "shapeGroup",
      "id": "E492003D-7AF6-4427-AE4B-C1785D8AAFBC"
    },
    {
      "class": "symbolInstance",
      "id": "F2280E74-FEFF-4DB4-9BFF-37DDD6C42B47"
    }
  ],
  "name": "✅ Icon ",
  "nameIsFixed": false,
  "resizingConstraint": 63,
  "resizingType": 0,
  "rotation": 0,
  "shouldBreakMaskChain": false,
  "style": {
    "_class": "style",
    "endMarkerType": 0,
    "miterLimit": 10,
    "startMarkerType": 0,
    "windingRule": 1
  },
  "userInfo": {
    "com.animaapp.stc-sketch-plugin": {
      "kModelPropertiesKey": {
      }
    }
  }
}